{"0": "3d-architecture", "1": "3d-cad", "2": "accounting-job-costing", "3": "affordable-housing", "4": "apartment-management", "5": "architectural-cad", "6": "bid-management-system", "7": "bid-management-systems", "8": "bim", "9": "commercial-real-estate", "10": "concrete-masonry", "11": "construction-accounting", "12": "construction-management", "13": "construction-project-management", "14": "construction-scheduling", "15": "cost-estimating", "16": "electrical-contractor", "17": "electrical-estimating", "18": "estimating", "19": "flooring-estimating", "20": "general-contractor", "21": "heavy-highway", "22": "hoa", "23": "home-inspection", "24": "homebuilder", "25": "homebuilder-crm", "26": "lease-accounting", "27": "lease-management", "28": "management-apps", "29": "manufactured-mobile-home-management", "30": "mechanical-and-hvac-estimating", "31": "paving", "32": "plumbing-estimating", "33": "project-scheduling", "34": "property-management", "35": "punch-list", "36": "real-estate-agency", "37": "real-estate-cma", "38": "real-estate-crm", "39": "real-estate-development", "40": "real-estate-management", "41": "real-estate-transaction-management", "42": "remodeling-estimating", "43": "rental-property-management", "44": "roofing", "45": "self-storage-facilities", "46": "sitework-excavating", "47": "solar", "48": "subcontractor", "49": "takeoff", "50": "timeshare", "51": "utility-management-systems", "52": "web-based-project-management", "53": "web-based-property-management"}